ph_geography/__init__.py
ph_geography/apps.py
ph_geography/models.py
ph_geography/fixtures/barangays.json
ph_geography/fixtures/municipalities.json
ph_geography/fixtures/provinces.json
ph_geography/fixtures/regions.json
ph_geography/management/__init__.py
ph_geography/management/commands/__init__.py
ph_geography/management/commands/phgeofixtures.py
ph_geography/migrations/0001_initial.py
ph_geography/migrations/__init__.py
tests/__init__.py
tests/settings.py
tests/test_commands.py
tests/test_models.py
tests/test_monkey_patching.py
django_ph_geography-1.0.0.dist-info/LICENSE
django_ph_geography-1.0.0.dist-info/METADATA
django_ph_geography-1.0.0.dist-info/WHEEL
django_ph_geography-1.0.0.dist-info/top_level.txt
django_ph_geography-1.0.0.dist-info/RECORD
