Metadata-Version: 2.1
Name: django-ph-geography
Version: 1.0.0
Summary: Philippine Geography models for Django
Home-page: https://github.com/josemarimanio/django-ph-geography/
Author: Jose Mari Manio
Author-email: josemari.manio@tutamail.com
License: MIT
Project-URL: Source Code, https://github.com/josemarimanio/django-ph-geography/
Platform: UNKNOWN
Classifier: Development Status :: 5 - Production/Stable
Classifier: Environment :: Web Environment
Classifier: Framework :: Django :: 1.11
Classifier: Framework :: Django :: 2.2
Classifier: Framework :: Django :: 3.0
Classifier: Framework :: Django :: 3.1
Classifier: Intended Audience :: Developers
Classifier: License :: OSI Approved :: MIT License
Classifier: Operating System :: OS Independent
Classifier: Programming Language :: Python :: 3
Classifier: Programming Language :: Python :: 3.4
Classifier: Programming Language :: Python :: 3.5
Classifier: Programming Language :: Python :: 3.6
Classifier: Programming Language :: Python :: 3.7
Classifier: Programming Language :: Python :: 3.8
Classifier: Topic :: Internet :: WWW/HTTP
Classifier: Topic :: Internet :: WWW/HTTP :: Dynamic Content
Requires-Python: >=3.4
Requires-Dist: django (>=1.11)
Provides-Extra: test
Requires-Dist: django-migration-testcase (==0.0.15) ; extra == 'test'
